signal_tl/__init__.py
signal_tl/_cext.cpython-314-x86_64-linux-gnu.so
pystlogic-0.1.3.post5.dist-info/METADATA
pystlogic-0.1.3.post5.dist-info/WHEEL
pystlogic-0.1.3.post5.dist-info/top_level.txt
pystlogic-0.1.3.post5.dist-info/RECORD
pystlogic-0.1.3.post5.dist-info/licenses/LICENSE
pystlogic-0.1.3.post5.dist-info/licenses/LICENSE-3rdParty
