Metadata-Version: 2.4
Name: pystlogic
Version: 0.1.3.post5
Summary: A library for efficiently working with Signal Temporal Logic (STL) and its quantitative semantics.
Home-page: https://github.com/davidhjp01/pystlogic
Author: Anand Balakrishnan
Author-email: anandbala1597@gmail.com
Maintainer: Hee Jong Park
Maintainer-email: hee.jong.park@dnv.com
Classifier: Programming Language :: Python :: 3 :: Only
Classifier: Programming Language :: Python :: 3.11
Classifier: Programming Language :: Python :: 3.12
Classifier: Programming Language :: Python :: 3.13
Classifier: Programming Language :: Python :: 3.14
Classifier: Programming Language :: C++
Classifier: License :: OSI Approved :: MIT License
Classifier: Intended Audience :: Science/Research
Requires-Python: <3.15,>=3.11
License-File: LICENSE
License-File: LICENSE-3rdParty
Dynamic: license-file
